[{"planCourseCnt":174,"realCourseCnt":108,"areaName":"JI省"},{"planCourseCnt":169,"realCourseCnt":112,"areaName":"SN省"},{"planCourseCnt":174,"realCourseCnt":139,"areaName":"WU省"},{"planCourseCnt":174,"realCourseCnt":115,"areaName":"OV省"},{"planCourseCnt":176,"realCourseCnt":117,"areaName":"KW省"},{"planCourseCnt":169,"realCourseCnt":143,"areaName":"TX省"},{"planCourseCnt":173,"realCourseCnt":107,"areaName":"WQ省"},{"planCourseCnt":161,"realCourseCnt":134,"areaName":"WR省"},{"planCourseCnt":191,"realCourseCnt":109,"areaName":"VK省"},{"planCourseCnt":165,"realCourseCnt":127,"areaName":"HW省"}]